streetfood_domain/.git/HEAD
streetfood_domain/.git/config
streetfood_domain/.git/description
streetfood_domain/.git/hooks/applypatch-msg.sample
streetfood_domain/.git/hooks/commit-msg.sample
streetfood_domain/.git/hooks/fsmonitor-watchman.sample
streetfood_domain/.git/hooks/post-update.sample
streetfood_domain/.git/hooks/pre-applypatch.sample
streetfood_domain/.git/hooks/pre-commit.sample
streetfood_domain/.git/hooks/pre-merge-commit.sample
streetfood_domain/.git/hooks/pre-push.sample
streetfood_domain/.git/hooks/pre-rebase.sample
streetfood_domain/.git/hooks/pre-receive.sample
streetfood_domain/.git/hooks/prepare-commit-msg.sample
streetfood_domain/.git/hooks/push-to-checkout.sample
streetfood_domain/.git/hooks/update.sample
streetfood_domain/.git/info/exclude
streetfood_domain/__init__.py
streetfood_domain/logic/order_state.py
streetfood_domain/models/order.py
streetfood_domain-0.1.0.dist-info/METADATA
streetfood_domain-0.1.0.dist-info/WHEEL
streetfood_domain-0.1.0.dist-info/RECORD
