Metadata-Version: 2.1
Name: streetfood-domain
Version: 0.1.0
Summary: 
Author: sazonov-src
Author-email: sazonov89vit@gmail.com
Requires-Python: >=3.10,<4.0
Classifier: Programming Language :: Python :: 3
Classifier: Programming Language :: Python :: 3.10
Classifier: Programming Language :: Python :: 3.11
Requires-Dist: pydantic (>=2.5.3,<3.0.0)
Requires-Dist: pytest (>=7.4.4,<8.0.0)
